omop_cdm_graphql/__init__.py
omop_cdm_graphql/console_helper.py
omop_cdm_graphql/constants.py
omop_cdm_graphql/database.py
omop_cdm_graphql/file_utils.py
omop_cdm_graphql/loader.py
omop_cdm_graphql/main.py
omop_cdm_graphql/models.py
omop_cdm_graphql/schema.py
omop_cdm_graphql/system_caller.py
omop_cdm_graphql/conf/config.yaml
omop_cdm_graphql-0.6.0.dist-info/AUTHORS.rst
omop_cdm_graphql-0.6.0.dist-info/METADATA
omop_cdm_graphql-0.6.0.dist-info/WHEEL
omop_cdm_graphql-0.6.0.dist-info/entry_points.txt
omop_cdm_graphql-0.6.0.dist-info/top_level.txt
omop_cdm_graphql-0.6.0.dist-info/RECORD
