Metadata-Version: 2.2
Name: omop-cdm-graphql
Version: 0.6.0
Summary: GraphQL service for exposing OMOP CDM records.
Author-email: Jaideep Sundaram <jai.python3@gmail.com>
Maintainer-email: Jaideep Sundaram <jai.python3@gmail.com>
License: Not open source
Project-URL: Homepage, https://github.com/jai-python3/omop-cdm-graphql
Keywords: OMOP,CDM,GraphQL
Classifier: Development Status :: 5 - Production/Stable
Classifier: Intended Audience :: Developers
Classifier: Natural Language :: English
Classifier: Programming Language :: Python :: 3.10
Requires-Python: >=3.10
License-File: AUTHORS.rst
Requires-Dist: Click>=7.0
Requires-Dist: PyYAML
Requires-Dist: Rich
Requires-Dist: singleton-decorator
Requires-Dist: strawberry-graphql
Requires-Dist: sqlalchemy
Requires-Dist: fastapi
Requires-Dist: uvicorn
Requires-Dist: databases[sqlite]
Requires-Dist: httpie
Provides-Extra: dev
Requires-Dist: coverage; extra == "dev"
Requires-Dist: mypy; extra == "dev"
Requires-Dist: pytest; extra == "dev"
Requires-Dist: ruff; extra == "dev"
